emerquant_dev-0.0.9.dist-info/METADATA
emerquant_dev-0.0.9.dist-info/top_level.txt
emerquant_dev-0.0.9.dist-info/RECORD
emerquant_dev-0.0.9.dist-info/WHEEL
emerquant/__init__.py
emerquant/sidecar/sidecar.cpython-38-x86_64-linux-gnu.so
emerquant/connections/__init__.py
emerquant/connections/binance/set_up_binance_connection.py
emerquant/connections/binance/binance_connection.cpython-38-x86_64-linux-gnu.so
emerquant/connections/binance/__init__.py
emerquant/connections/yahoo_finance/yahoo_finance_connection.cpython-38-x86_64-linux-gnu.so
emerquant/connections/yahoo_finance/set_up_yahoo_finance_connection.py
emerquant/connections/yahoo_finance/__init__.py
emerquant/finML/optimal_entry_models.cpython-38-x86_64-linux-gnu.so
emerquant/finML/__init__.py
emerquant/finML/feature_engineer.cpython-38-x86_64-linux-gnu.so
emerquant/finML/set_up_finML.py
emerquant/utils/__init__.py
emerquant/utils/pickling/rebuilds.py
emerquant/utils/pickling/__init__.py
emerquant/utils/results/set_up_results.py
emerquant/utils/results/__init__.py
emerquant/utils/results/factor_results.cpython-38-x86_64-linux-gnu.so
emerquant/utils/filters/security_filter.cpython-38-x86_64-linux-gnu.so
emerquant/utils/filters/set_up_filters.py
emerquant/utils/filters/__init__.py
emerquant/utils/performance_reporting/__init__.py
emerquant/utils/inference/inference.cpython-38-x86_64-linux-gnu.so
emerquant/utils/inference/__init__.py
emerquant/utils/inference/set_up_inference.py
emerquant/factors/__init__.py
emerquant/factors/technical/set_up_technical_mean_reversion_factors.py
emerquant/factors/technical/mean_reversion.cpython-38-x86_64-linux-gnu.so
emerquant/factors/technical/__init__.py
notebooks/__init__.py
