Metadata-Version: 2.1
Name: emerquant-dev
Version: 0.0.9
Summary: description
Home-page: https://www.emerfin.io
Author: EmerFin
Author-email: admin@emerfin.io
License: UNKNOWN
Platform: UNKNOWN
Requires-Dist: aiohttp (==3.8.1)
Requires-Dist: aiosignal (==1.2.0)
Requires-Dist: alembic (==1.7.6)
Requires-Dist: async-timeout (==4.0.2)
Requires-Dist: attrs (==21.4.0)
Requires-Dist: autopage (==0.5.0)
Requires-Dist: backports.zoneinfo (==0.2.1)
Requires-Dist: beautifulsoup4 (==4.10.0)
Requires-Dist: certifi (==2021.10.8)
Requires-Dist: charset-normalizer (==2.0.11)
Requires-Dist: cliff (==3.10.0)
Requires-Dist: cmaes (==0.8.2)
Requires-Dist: cmd2 (==2.3.3)
Requires-Dist: colorama (==0.4.4)
Requires-Dist: colorlog (==6.6.0)
Requires-Dist: cycler (==0.11.0)
Requires-Dist: Cython (==0.29.27)
Requires-Dist: dateparser (==1.1.0)
Requires-Dist: fonttools (==4.29.1)
Requires-Dist: frozenlist (==1.3.0)
Requires-Dist: greenlet (==1.1.2)
Requires-Dist: idna (==3.3)
Requires-Dist: importlib-metadata (==4.10.1)
Requires-Dist: importlib-resources (==5.4.0)
Requires-Dist: joblib (==1.1.0)
Requires-Dist: kiwisolver (==1.3.2)
Requires-Dist: lxml (==4.7.1)
Requires-Dist: Mako (==1.1.6)
Requires-Dist: MarkupSafe (==2.0.1)
Requires-Dist: matplotlib (==3.5.1)
Requires-Dist: multidict (==6.0.2)
Requires-Dist: numpy (==1.22.2)
Requires-Dist: optuna (==2.10.0)
Requires-Dist: packaging (==21.3)
Requires-Dist: pandas (==1.4.0)
Requires-Dist: pandas-datareader (==0.10.0)
Requires-Dist: pbr (==5.8.1)
Requires-Dist: Pillow (==9.0.1)
Requires-Dist: prettytable (==3.0.0)
Requires-Dist: pycryptodome (==3.14.1)
Requires-Dist: pyparsing (==3.0.7)
Requires-Dist: pyperclip (==1.8.2)
Requires-Dist: pyreadline3 (==3.4.1)
Requires-Dist: python-binance (==1.0.15)
Requires-Dist: python-dateutil (==2.8.2)
Requires-Dist: pytz (==2021.3)
Requires-Dist: pytz-deprecation-shim (==0.1.0.post0)
Requires-Dist: PyYAML (==6.0)
Requires-Dist: regex (==2022.1.18)
Requires-Dist: requests (==2.27.1)
Requires-Dist: scikit-learn (==1.0.2)
Requires-Dist: scipy (==1.7.3)
Requires-Dist: seaborn (==0.11.2)
Requires-Dist: six (==1.16.0)
Requires-Dist: soupsieve (==2.3.1)
Requires-Dist: SQLAlchemy (==1.4.31)
Requires-Dist: stevedore (==3.5.0)
Requires-Dist: TA-Lib (==0.4.24)
Requires-Dist: tabulate (==0.8.9)
Requires-Dist: threadpoolctl (==3.1.0)
Requires-Dist: timeseriescv (==0.2)
Requires-Dist: tqdm (==4.62.3)
Requires-Dist: tzdata (==2021.5)
Requires-Dist: tzlocal (==4.1)
Requires-Dist: ujson (==5.1.0)
Requires-Dist: urllib3 (==1.26.8)
Requires-Dist: wcwidth (==0.2.5)
Requires-Dist: websockets (==9.1)
Requires-Dist: yarl (==1.7.2)
Requires-Dist: yfinance (==0.1.70)
Requires-Dist: zipp (==3.7.0)
Requires-Dist: PyObjC ; platform_system == "Darwin"
Requires-Dist: PyGObject ; platform_system == "Linux"
